{
  "names": {
    "en_US": "FZSONIC Battery Z37-310-76 75kWh"
  },
  "image_url": "https://tags.ioxio.dev/images/fzsonic-battery.png",
  "supported_dataproducts": [
    {
      "path": "DigitalProductPassport/Battery/CarbonFootprint_v0.1",
      "source": "dpp_demo"
    },
    {
      "path": "DigitalProductPassport/Battery/ManufacturingDataSheet_v0.1",
      "source": "dpp_demo"
    },
    {
      "path": "DigitalProductPassport/Battery/HealthData_v0.1",
      "source": "dpp_demo"
    }
  ]
}
